aas_core3_protobuf/__init__.py
aas_core3_protobuf/pbization.py
aas_core3_protobuf/types_pb2.py
aas_core3_protobuf/types_pb2.pyi
aas_core3.0_protobuf-0.0.2.dist-info/AUTHORS
aas_core3.0_protobuf-0.0.2.dist-info/LICENSE
aas_core3.0_protobuf-0.0.2.dist-info/METADATA
aas_core3.0_protobuf-0.0.2.dist-info/WHEEL
aas_core3.0_protobuf-0.0.2.dist-info/top_level.txt
aas_core3.0_protobuf-0.0.2.dist-info/RECORD
