Metadata-Version: 2.1
Name: aas-core3.0-protobuf
Version: 0.0.2
Summary: Convert Asset Administration Shells V3.0 between Python and ProtoBuf objects.
Author-email: Marko Ristin <marko@ristin.ch>
Project-URL: repository, https://github.com/aas-core-works/aas-core3.0-python-protobuf
Classifier: Development Status :: 5 - Production/Stable
Classifier: Intended Audience :: Developers
Classifier: License :: OSI Approved :: MIT License
Classifier: Programming Language :: Python :: 3.8
Classifier: Programming Language :: Python :: 3.9
Classifier: Programming Language :: Python :: 3.10
Classifier: Programming Language :: Python :: 3.11
Classifier: Programming Language :: Python :: 3.12
Requires-Python: >=3.8
License-File: LICENSE
License-File: AUTHORS
Requires-Dist: aas-core3.0 <2,>=1
Requires-Dist: protobuf >=5
